cairo_type_hints/__init__.py
cairo_type_hints/cairo.ebnf
cairo_type_hints/console.py
cairo_type_hints/generate.py
cairo_type_hints/parser.py
cairo_type_hints-0.1.7.dist-info/LICENSE
cairo_type_hints-0.1.7.dist-info/METADATA
cairo_type_hints-0.1.7.dist-info/WHEEL
cairo_type_hints-0.1.7.dist-info/entry_points.txt
cairo_type_hints-0.1.7.dist-info/top_level.txt
cairo_type_hints-0.1.7.dist-info/RECORD
