Metadata-Version: 2.1
Name: cairo-type-hints
Version: 0.1.7
Summary: Generate type hints for Cairo lang
Home-page: https://github.com/playmint/cairo-type-hints
Author: Chris Baker
Author-email: lxufimdu@pm.me
License: LICENSE
Classifier: Development Status :: 3 - Alpha
Classifier: Environment :: Console
Classifier: Environment :: MacOS X
Classifier: Environment :: Win32 (MS Windows)
Classifier: Environment :: X11 Applications
Classifier: Intended Audience :: Developers
Classifier: License :: OSI Approved :: MIT License
Classifier: Operating System :: MacOS :: MacOS X
Classifier: Operating System :: Microsoft :: Windows
Classifier: Operating System :: POSIX :: Linux
Classifier: Programming Language :: Python :: 3.9
Classifier: Topic :: Software Development
License-File: LICENSE
Requires-Dist: lark (==0.12.0)
